setup.cfg
setup.py
resourceSet_for_execo/__init__.py
resourceSet_for_execo/resourceSet.py
resourceSet_for_execo.egg-info/PKG-INFO
resourceSet_for_execo.egg-info/SOURCES.txt
resourceSet_for_execo.egg-info/dependency_links.txt
resourceSet_for_execo.egg-info/top_level.txt