Metadata-Version: 1.1
Name: resourceSet-for-execo
Version: 0.1
Summary: resourceSet for http://execo.gforge.inria.fr/doc/latest-stable/ | School project at Polytech Grenoble : http://air.imag.fr/index.php/ExperimentControl
Home-page: https://github.com/TimotheeLemaire/resourceSet_for_execo
Author: Timothee Lemaire and Nicolas Homberg
Author-email: nshg117@gmail.com
License: UNKNOWN
Download-URL: https://github.com/TimotheeLemaire/resourceSet_for_execo/archive/0.1.tar.gz
Keywords: testing,logging,Execo,grid5000,tak tuk
Platform: UNKNOWN
